visky/__init__.py
visky/hadec_on_azel_grid.py
visky/location.py
visky/py.typed
visky/utils.py
visky-0.0.1.dist-info/WHEEL
visky-0.0.1.dist-info/METADATA
visky-0.0.1.dist-info/RECORD
