Metadata-Version: 2.3
Name: visky
Version: 0.0.1
Summary: Given an earth location, plot lines of constant hour angle and declination on an azimuth-elevation grid
Requires-Dist: astropy>=7.1.1
Requires-Dist: numpy>=2.3.4
Requires-Dist: plotly>=6.3.1
Requires-Python: >=3.12
